{
    "palavras":{
        "nivel1": [
            {"id":1, "palavra": "sagaz"},
            {"id":2, "palavra": "negro"},
            {"id":3, "palavra": "mexer"},
            {"id":4, "palavra": "termo"},
            {"id":5, "palavra": "nobre"},
            {"id":6, "palavra": "senso"},
            {"id":7, "palavra": "algoz"},
            {"id":8, "palavra": "afeto"},
            {"id":9, "palavra": "plena"},
            {"id":10, "palavra": "mútua"},
            {"id":11, "palavra": "tênue"},
            {"id":12, "palavra": "sutil"},
            {"id":13, "palavra": "vigor"},
            {"id":14, "palavra": "fazer"},
            {"id":15, "palavra": "assim"},
            {"id":16, "palavra": "audaz"},
            {"id":17, "palavra": "sanar"},
            {"id":18, "palavra": "inato"},
            {"id":19, "palavra": "cerne"},
            {"id":20, "palavra": "fosse"}],
        "nivel2":[
            {"id":21, "palavra": "ideia"},
            {"id":22, "palavra": "poder"},
            {"id":23, "palavra": "moral"},
            {"id":24, "palavra": "desde"},
            {"id":25, "palavra": "muito"},
            {"id":26, "palavra": "justo"},
            {"id":27, "palavra": "torpe"},
            {"id":28, "palavra": "honra"},
            {"id":29, "palavra": "sobre"},
            {"id":30, "palavra": "fútil"},
            {"id":31, "palavra": "anexo"},
            {"id":32, "palavra": "etnia"},
            {"id":33, "palavra": "sonho"},
            {"id":34, "palavra": "tange"},
            {"id":34, "palavra": "amigo"},
            {"id":36, "palavra": "lapso"},
            {"id":37, "palavra": "expor"},
            {"id":38, "palavra": "haver"},
            {"id":39, "palavra": "tempo"},
            {"id":40, "palavra": "dengo"}]
    }
}